setup.py
prob_by_suraj/Binomialdistribution.py
prob_by_suraj/Gaussiandistribution.py
prob_by_suraj/Generaldistribution.py
prob_by_suraj/__init__.py
prob_by_suraj.egg-info/PKG-INFO
prob_by_suraj.egg-info/SOURCES.txt
prob_by_suraj.egg-info/dependency_links.txt
prob_by_suraj.egg-info/not-zip-safe
prob_by_suraj.egg-info/top_level.txt